{"is_source_file": false, "format": "", "description": "", "external_files": [], "external_methods": [], "published": [], "classes": [], "methods": [], "calls": [], "search-terms": [], "state": 2, "file_id": 3, "knowledge_revision": 90, "git_revision": "6a1a5e5bbb09f4321a34ec2bec7626035bc98339", "hash": "5936fd793f7fb55b837f5a63ee9369ff", "format-version": 4, "code-base-name": "notes_frontend", "filename": "notes_frontend/analysis_options.yaml", "revision_history": [{"90": "6a1a5e5bbb09f4321a34ec2bec7626035bc98339"}]}